seasushi/__init__.py
seasushi/confs/config_plot_regular_ww3.yaml
seasushi/data/ww3_global_example.nc
seasushi/tests/__init__.py
seasushi/tests/data/ww3_global_example.nc
seasushi/tests/example1.ipynb
seasushi/tests/extract_nc2nc_1timestep.py
seasushi/tests/figs/hs_plot_2003-07-01-00h.png
seasushi/tests/figs/t01_plot_2003-07-01-00h.png
seasushi/tests/plotWW3_global.py
seasushi/tests/test_default.py
seasushi/tools.py
seasushi/ww3.py
seasushi-0.1.1.dist-info/METADATA
seasushi-0.1.1.dist-info/WHEEL
seasushi-0.1.1.dist-info/RECORD
