Metadata-Version: 2.1
Name: seasushi
Version: 0.1.1
Summary: Functions and scripts collection for metocean numerical models, data plots, and analyses
Author: jtcarvalho
Author-email: jtcarvalho@gmail.com
Requires-Python: >=3.12,<4.0
Classifier: Programming Language :: Python :: 3
Classifier: Programming Language :: Python :: 3.12
Classifier: Programming Language :: Python :: 3.13
Requires-Dist: cartopy (>=0.24.1,<0.25.0)
Requires-Dist: glob2 (>=0.7,<0.8)
Requires-Dist: h5netcdf (>=1.5.0,<2.0.0)
Requires-Dist: matplotlib (>=3.10.0,<4.0.0)
Requires-Dist: natsort (>=8.4.0,<9.0.0)
Requires-Dist: netcdf4 (>=1.7.2,<2.0.0)
Requires-Dist: numpy (>=2.2.3,<3.0.0)
Requires-Dist: pandas (>=2.2.3,<3.0.0)
Requires-Dist: pyyaml (>=6.0.2,<7.0.0)
Requires-Dist: scipy (>=1.15.2,<2.0.0)
Requires-Dist: simplejson (>=3.20.1,<4.0.0)
Requires-Dist: xarray (>=2025.1.2,<2026.0.0)
